dv_ui_components/AltBadge.py
dv_ui_components/DvUiComponents.py
dv_ui_components/DvpAffix.py
dv_ui_components/DvpBreadcrumb.py
dv_ui_components/DvpButton.py
dv_ui_components/DvpCard.py
dv_ui_components/DvpCheckbox.py
dv_ui_components/DvpCheckboxGroup.py
dv_ui_components/DvpCol.py
dv_ui_components/DvpCollapse.py
dv_ui_components/DvpContent.py
dv_ui_components/DvpDateRangePicker.py
dv_ui_components/DvpDescriptionItem.py
dv_ui_components/DvpDescriptions.py
dv_ui_components/DvpDivider.py
dv_ui_components/DvpEntryForm.py
dv_ui_components/DvpFooter.py
dv_ui_components/DvpForm.py
dv_ui_components/DvpFormItem.py
dv_ui_components/DvpHeader.py
dv_ui_components/DvpIcon.py
dv_ui_components/DvpInput.py
dv_ui_components/DvpInputNumber.py
dv_ui_components/DvpLayout.py
dv_ui_components/DvpMenu.py
dv_ui_components/DvpModal.py
dv_ui_components/DvpMultiInput.py
dv_ui_components/DvpPagination.py
dv_ui_components/DvpParagraph.py
dv_ui_components/DvpRadioGroup.py
dv_ui_components/DvpRow.py
dv_ui_components/DvpSelect.py
dv_ui_components/DvpSider.py
dv_ui_components/DvpSiderTemplate.py
dv_ui_components/DvpSlider.py
dv_ui_components/DvpSpace.py
dv_ui_components/DvpSpinner.py
dv_ui_components/DvpStyle.py
dv_ui_components/DvpSwitch.py
dv_ui_components/DvpTable.py
dv_ui_components/DvpTag.py
dv_ui_components/DvpText.py
dv_ui_components/DvpTimeline.py
dv_ui_components/DvpTitle.py
dv_ui_components/ExecuteJs.py
dv_ui_components/RawHTML.py
dv_ui_components/Theme.py
dv_ui_components/__init__.py
dv_ui_components/_imports_.py
dv_ui_components/async-DvUiComponents.js
dv_ui_components/async-DvUiComponents.js.map
dv_ui_components/dv_ui_components.min.js
dv_ui_components/dv_ui_components.min.js.map
dv_ui_components/metadata.json
dv_ui_components/package-info.json
dv_ui_components-0.1.4.dist-info/LICENSE
dv_ui_components-0.1.4.dist-info/METADATA
dv_ui_components-0.1.4.dist-info/WHEEL
dv_ui_components-0.1.4.dist-info/top_level.txt
dv_ui_components-0.1.4.dist-info/RECORD
