Metadata-Version: 2.1
Name: dv-ui-components
Version: 0.1.4
Summary: Customized Dash Components based on Ant Design Componenets
Author: Anya Ip <anyakurapica@gmail.com>
License: MIT
Classifier: Framework :: Dash
License-File: LICENSE
